{
  "_format": "hh-sol-cache-2",
  "files": {
    "D:\\Dynamic_Arbitrage_FlashLoan_Trading_Bot-main\\contracts\\Arbitrage.sol": {
      "lastModificationDate": 1780628145934,
      "contentHash": "134d37d1d21e4418957cec614f3e529c",
      "sourceName": "contracts/Arbitrage.sol",
      "solcConfig": {
        "version": "0.8.18",
        "settings": {
          "optimizer": {
            "enabled": false,
            "runs": 200
          },
          "outputSelection": {
            "*": {
              "*": [
                "abi",
                "evm.bytecode",
                "evm.deployedBytecode",
                "evm.methodIdentifiers",
                "metadata"
              ],
              "": [
                "ast"
              ]
            }
          }
        }
      },
      "imports": [
        "@balancer-labs/v2-interfaces/contracts/vault/IVault.sol",
        "@balancer-labs/v2-interfaces/contracts/vault/IFlashLoanRecipient.sol",
        "@uniswap/v2-periphery/contracts/interfaces/IUniswapV2Router02.sol",
        "@openzeppelin/contracts/security/ReentrancyGuard.sol",
        "@openzeppelin/contracts/security/Pausable.sol"
      ],
      "versionPragmas": [
        "0.8.18"
      ],
      "artifacts": [
        "Arbitrage"
      ]
    },
    "D:\\Dynamic_Arbitrage_FlashLoan_Trading_Bot-main\\node_modules\\@openzeppelin\\contracts\\security\\ReentrancyGuard.sol": {
      "lastModificationDate": 1780710381956,
      "contentHash": "1535f8c0c68463f8c1b5239f7584e71f",
      "sourceName": "@openzeppelin/contracts/security/ReentrancyGuard.sol",
      "solcConfig": {
        "version": "0.8.18",
        "settings": {
          "optimizer": {
            "enabled": false,
            "runs": 200
          },
          "outputSelection": {
            "*": {
              "*": [
                "abi",
                "evm.bytecode",
                "evm.deployedBytecode",
                "evm.methodIdentifiers",
                "metadata"
              ],
              "": [
                "ast"
              ]
            }
          }
        }
      },
      "imports": [],
      "versionPragmas": [
        "^0.8.0"
      ],
      "artifacts": [
        "ReentrancyGuard"
      ]
    },
    "D:\\Dynamic_Arbitrage_FlashLoan_Trading_Bot-main\\node_modules\\@uniswap\\v2-periphery\\contracts\\interfaces\\IUniswapV2Router02.sol": {
      "lastModificationDate": 1780710380373,
      "contentHash": "3fd36426274a5b35f7e702f87ba08a8e",
      "sourceName": "@uniswap/v2-periphery/contracts/interfaces/IUniswapV2Router02.sol",
      "solcConfig": {
        "version": "0.8.18",
        "settings": {
          "optimizer": {
            "enabled": false,
            "runs": 200
          },
          "outputSelection": {
            "*": {
              "*": [
                "abi",
                "evm.bytecode",
                "evm.deployedBytecode",
                "evm.methodIdentifiers",
                "metadata"
              ],
              "": [
                "ast"
              ]
            }
          }
        }
      },
      "imports": [
        "./IUniswapV2Router01.sol"
      ],
      "versionPragmas": [
        ">=0.6.2"
      ],
      "artifacts": [
        "IUniswapV2Router02"
      ]
    },
    "D:\\Dynamic_Arbitrage_FlashLoan_Trading_Bot-main\\node_modules\\@openzeppelin\\contracts\\security\\Pausable.sol": {
      "lastModificationDate": 1780710381944,
      "contentHash": "25c8108f36fdd472bc78d4c4af240c11",
      "sourceName": "@openzeppelin/contracts/security/Pausable.sol",
      "solcConfig": {
        "version": "0.8.18",
        "settings": {
          "optimizer": {
            "enabled": false,
            "runs": 200
          },
          "outputSelection": {
            "*": {
              "*": [
                "abi",
                "evm.bytecode",
                "evm.deployedBytecode",
                "evm.methodIdentifiers",
                "metadata"
              ],
              "": [
                "ast"
              ]
            }
          }
        }
      },
      "imports": [
        "../utils/Context.sol"
      ],
      "versionPragmas": [
        "^0.8.0"
      ],
      "artifacts": [
        "Pausable"
      ]
    },
    "D:\\Dynamic_Arbitrage_FlashLoan_Trading_Bot-main\\node_modules\\@balancer-labs\\v2-interfaces\\contracts\\vault\\IVault.sol": {
      "lastModificationDate": 1780710381718,
      "contentHash": "46a20a7701464ab9c62cb907614fd3bb",
      "sourceName": "@balancer-labs/v2-interfaces/contracts/vault/IVault.sol",
      "solcConfig": {
        "version": "0.8.18",
        "settings": {
          "optimizer": {
            "enabled": false,
            "runs": 200
          },
          "outputSelection": {
            "*": {
              "*": [
                "abi",
                "evm.bytecode",
                "evm.deployedBytecode",
                "evm.methodIdentifiers",
                "metadata"
              ],
              "": [
                "ast"
              ]
            }
          }
        }
      },
      "imports": [
        "../solidity-utils/openzeppelin/IERC20.sol",
        "../solidity-utils/helpers/IAuthentication.sol",
        "../solidity-utils/helpers/ISignaturesValidator.sol",
        "../solidity-utils/helpers/ITemporarilyPausable.sol",
        "../solidity-utils/misc/IWETH.sol",
        "./IAsset.sol",
        "./IAuthorizer.sol",
        "./IFlashLoanRecipient.sol",
        "./IProtocolFeesCollector.sol"
      ],
      "versionPragmas": [
        ">=0.7.0 <0.9.0"
      ],
      "artifacts": [
        "IVault"
      ]
    },
    "D:\\Dynamic_Arbitrage_FlashLoan_Trading_Bot-main\\node_modules\\@balancer-labs\\v2-interfaces\\contracts\\vault\\IFlashLoanRecipient.sol": {
      "lastModificationDate": 1780710381693,
      "contentHash": "31e2c769fc0ac25db2d9b46225793f01",
      "sourceName": "@balancer-labs/v2-interfaces/contracts/vault/IFlashLoanRecipient.sol",
      "solcConfig": {
        "version": "0.8.18",
        "settings": {
          "optimizer": {
            "enabled": false,
            "runs": 200
          },
          "outputSelection": {
            "*": {
              "*": [
                "abi",
                "evm.bytecode",
                "evm.deployedBytecode",
                "evm.methodIdentifiers",
                "metadata"
              ],
              "": [
                "ast"
              ]
            }
          }
        }
      },
      "imports": [
        "../solidity-utils/openzeppelin/IERC20.sol"
      ],
      "versionPragmas": [
        ">=0.7.0 <0.9.0"
      ],
      "artifacts": [
        "IFlashLoanRecipient"
      ]
    },
    "D:\\Dynamic_Arbitrage_FlashLoan_Trading_Bot-main\\node_modules\\@uniswap\\v2-periphery\\contracts\\interfaces\\IUniswapV2Router01.sol": {
      "lastModificationDate": 1780710380368,
      "contentHash": "95d8729b2c698dc663322167b3c085fe",
      "sourceName": "@uniswap/v2-periphery/contracts/interfaces/IUniswapV2Router01.sol",
      "solcConfig": {
        "version": "0.8.18",
        "settings": {
          "optimizer": {
            "enabled": false,
            "runs": 200
          },
          "outputSelection": {
            "*": {
              "*": [
                "abi",
                "evm.bytecode",
                "evm.deployedBytecode",
                "evm.methodIdentifiers",
                "metadata"
              ],
              "": [
                "ast"
              ]
            }
          }
        }
      },
      "imports": [],
      "versionPragmas": [
        ">=0.6.2"
      ],
      "artifacts": [
        "IUniswapV2Router01"
      ]
    },
    "D:\\Dynamic_Arbitrage_FlashLoan_Trading_Bot-main\\node_modules\\@openzeppelin\\contracts\\utils\\Context.sol": {
      "lastModificationDate": 1780710380870,
      "contentHash": "f07feb4a44b1a4872370da5aa70e8e46",
      "sourceName": "@openzeppelin/contracts/utils/Context.sol",
      "solcConfig": {
        "version": "0.8.18",
        "settings": {
          "optimizer": {
            "enabled": false,
            "runs": 200
          },
          "outputSelection": {
            "*": {
              "*": [
                "abi",
                "evm.bytecode",
                "evm.deployedBytecode",
                "evm.methodIdentifiers",
                "metadata"
              ],
              "": [
                "ast"
              ]
            }
          }
        }
      },
      "imports": [],
      "versionPragmas": [
        "^0.8.0"
      ],
      "artifacts": [
        "Context"
      ]
    },
    "D:\\Dynamic_Arbitrage_FlashLoan_Trading_Bot-main\\node_modules\\@balancer-labs\\v2-interfaces\\contracts\\solidity-utils\\helpers\\IAuthentication.sol": {
      "lastModificationDate": 1780710381169,
      "contentHash": "63f8c7b7a4ac329c8104063a025a991b",
      "sourceName": "@balancer-labs/v2-interfaces/contracts/solidity-utils/helpers/IAuthentication.sol",
      "solcConfig": {
        "version": "0.8.18",
        "settings": {
          "optimizer": {
            "enabled": false,
            "runs": 200
          },
          "outputSelection": {
            "*": {
              "*": [
                "abi",
                "evm.bytecode",
                "evm.deployedBytecode",
                "evm.methodIdentifiers",
                "metadata"
              ],
              "": [
                "ast"
              ]
            }
          }
        }
      },
      "imports": [],
      "versionPragmas": [
        ">=0.7.0 <0.9.0"
      ],
      "artifacts": [
        "IAuthentication"
      ]
    },
    "D:\\Dynamic_Arbitrage_FlashLoan_Trading_Bot-main\\node_modules\\@balancer-labs\\v2-interfaces\\contracts\\solidity-utils\\helpers\\ISignaturesValidator.sol": {
      "lastModificationDate": 1780710381190,
      "contentHash": "48de5f36515898c9e9ddcd00f651ef86",
      "sourceName": "@balancer-labs/v2-interfaces/contracts/solidity-utils/helpers/ISignaturesValidator.sol",
      "solcConfig": {
        "version": "0.8.18",
        "settings": {
          "optimizer": {
            "enabled": false,
            "runs": 200
          },
          "outputSelection": {
            "*": {
              "*": [
                "abi",
                "evm.bytecode",
                "evm.deployedBytecode",
                "evm.methodIdentifiers",
                "metadata"
              ],
              "": [
                "ast"
              ]
            }
          }
        }
      },
      "imports": [],
      "versionPragmas": [
        ">=0.7.0 <0.9.0"
      ],
      "artifacts": [
        "ISignaturesValidator"
      ]
    },
    "D:\\Dynamic_Arbitrage_FlashLoan_Trading_Bot-main\\node_modules\\@balancer-labs\\v2-interfaces\\contracts\\solidity-utils\\misc\\IWETH.sol": {
      "lastModificationDate": 1780710381215,
      "contentHash": "8347e7eef0bb47de8851ecbcf8eb590c",
      "sourceName": "@balancer-labs/v2-interfaces/contracts/solidity-utils/misc/IWETH.sol",
      "solcConfig": {
        "version": "0.8.18",
        "settings": {
          "optimizer": {
            "enabled": false,
            "runs": 200
          },
          "outputSelection": {
            "*": {
              "*": [
                "abi",
                "evm.bytecode",
                "evm.deployedBytecode",
                "evm.methodIdentifiers",
                "metadata"
              ],
              "": [
                "ast"
              ]
            }
          }
        }
      },
      "imports": [
        "../openzeppelin/IERC20.sol"
      ],
      "versionPragmas": [
        ">=0.7.0 <0.9.0"
      ],
      "artifacts": [
        "IWETH"
      ]
    },
    "D:\\Dynamic_Arbitrage_FlashLoan_Trading_Bot-main\\node_modules\\@balancer-labs\\v2-interfaces\\contracts\\solidity-utils\\helpers\\ITemporarilyPausable.sol": {
      "lastModificationDate": 1780710381199,
      "contentHash": "5a94e6420fe95c3e0fa16e78fb8f74c3",
      "sourceName": "@balancer-labs/v2-interfaces/contracts/solidity-utils/helpers/ITemporarilyPausable.sol",
      "solcConfig": {
        "version": "0.8.18",
        "settings": {
          "optimizer": {
            "enabled": false,
            "runs": 200
          },
          "outputSelection": {
            "*": {
              "*": [
                "abi",
                "evm.bytecode",
                "evm.deployedBytecode",
                "evm.methodIdentifiers",
                "metadata"
              ],
              "": [
                "ast"
              ]
            }
          }
        }
      },
      "imports": [],
      "versionPragmas": [
        ">=0.7.0 <0.9.0"
      ],
      "artifacts": [
        "ITemporarilyPausable"
      ]
    },
    "D:\\Dynamic_Arbitrage_FlashLoan_Trading_Bot-main\\node_modules\\@balancer-labs\\v2-interfaces\\contracts\\solidity-utils\\openzeppelin\\IERC20.sol": {
      "lastModificationDate": 1780710381232,
      "contentHash": "028dddcf9b178b241401b1ae8126c903",
      "sourceName": "@balancer-labs/v2-interfaces/contracts/solidity-utils/openzeppelin/IERC20.sol",
      "solcConfig": {
        "version": "0.8.18",
        "settings": {
          "optimizer": {
            "enabled": false,
            "runs": 200
          },
          "outputSelection": {
            "*": {
              "*": [
                "abi",
                "evm.bytecode",
                "evm.deployedBytecode",
                "evm.methodIdentifiers",
                "metadata"
              ],
              "": [
                "ast"
              ]
            }
          }
        }
      },
      "imports": [],
      "versionPragmas": [
        ">=0.7.0 <0.9.0"
      ],
      "artifacts": [
        "IERC20"
      ]
    },
    "D:\\Dynamic_Arbitrage_FlashLoan_Trading_Bot-main\\node_modules\\@balancer-labs\\v2-interfaces\\contracts\\vault\\IAuthorizer.sol": {
      "lastModificationDate": 1780710381678,
      "contentHash": "03599610995051c98edd4f72102136b2",
      "sourceName": "@balancer-labs/v2-interfaces/contracts/vault/IAuthorizer.sol",
      "solcConfig": {
        "version": "0.8.18",
        "settings": {
          "optimizer": {
            "enabled": false,
            "runs": 200
          },
          "outputSelection": {
            "*": {
              "*": [
                "abi",
                "evm.bytecode",
                "evm.deployedBytecode",
                "evm.methodIdentifiers",
                "metadata"
              ],
              "": [
                "ast"
              ]
            }
          }
        }
      },
      "imports": [],
      "versionPragmas": [
        ">=0.7.0 <0.9.0"
      ],
      "artifacts": [
        "IAuthorizer"
      ]
    },
    "D:\\Dynamic_Arbitrage_FlashLoan_Trading_Bot-main\\node_modules\\@balancer-labs\\v2-interfaces\\contracts\\vault\\IAsset.sol": {
      "lastModificationDate": 1780710381671,
      "contentHash": "20c61578e7416055512409a25576fb1a",
      "sourceName": "@balancer-labs/v2-interfaces/contracts/vault/IAsset.sol",
      "solcConfig": {
        "version": "0.8.18",
        "settings": {
          "optimizer": {
            "enabled": false,
            "runs": 200
          },
          "outputSelection": {
            "*": {
              "*": [
                "abi",
                "evm.bytecode",
                "evm.deployedBytecode",
                "evm.methodIdentifiers",
                "metadata"
              ],
              "": [
                "ast"
              ]
            }
          }
        }
      },
      "imports": [],
      "versionPragmas": [
        ">=0.7.0 <0.9.0"
      ],
      "artifacts": [
        "IAsset"
      ]
    },
    "D:\\Dynamic_Arbitrage_FlashLoan_Trading_Bot-main\\node_modules\\@balancer-labs\\v2-interfaces\\contracts\\vault\\IProtocolFeesCollector.sol": {
      "lastModificationDate": 1780710381712,
      "contentHash": "26a23f2667431cfc1ea8aa5e69edef63",
      "sourceName": "@balancer-labs/v2-interfaces/contracts/vault/IProtocolFeesCollector.sol",
      "solcConfig": {
        "version": "0.8.18",
        "settings": {
          "optimizer": {
            "enabled": false,
            "runs": 200
          },
          "outputSelection": {
            "*": {
              "*": [
                "abi",
                "evm.bytecode",
                "evm.deployedBytecode",
                "evm.methodIdentifiers",
                "metadata"
              ],
              "": [
                "ast"
              ]
            }
          }
        }
      },
      "imports": [
        "../solidity-utils/openzeppelin/IERC20.sol",
        "./IVault.sol",
        "./IAuthorizer.sol"
      ],
      "versionPragmas": [
        ">=0.7.0 <0.9.0"
      ],
      "artifacts": [
        "IProtocolFeesCollector"
      ]
    }
  }
}
